pywebdev/__init__.py
pywebdev/writeHtml.py
pywebdev-0.1.1.dist-info/METADATA
pywebdev-0.1.1.dist-info/WHEEL
pywebdev-0.1.1.dist-info/top_level.txt
pywebdev-0.1.1.dist-info/RECORD
