Metadata-Version: 2.1
Name: pywebdev
Version: 0.1.1
Summary: Biblioteca de Desenvolvimento Web Python - Um kit abrangente para criar aplicativos da web de alto desempenho.
Home-page: UNKNOWN
Author: icarogamer2001
Author-email: UNKNOWN
License: UNKNOWN
Platform: UNKNOWN
Classifier: Development Status :: 3 - Alpha
Classifier: Intended Audience :: Developers
Classifier: License :: OSI Approved :: MIT License
Classifier: Programming Language :: Python
Classifier: Programming Language :: Python :: 3
Classifier: Programming Language :: Python :: 3.1
Classifier: Topic :: Software Development
Classifier: Topic :: Software Development :: Libraries :: Python Modules
Requires-Python: >=3.1
